{
  "ANGAD RESTORENT BALICHA": "",
  "BAJRANG DUDH DAIRY & GEN (RK PURAM)": "",
  "BIKANER PRO. STORE RK PURAM": "",
  "FRIENDS ICE CREAM (UMARDA)": "",
  "HEALTH CARE PHARMACY-Sect-3": "",
  "JAI AMBAY JODHPUR SWEETS & BAKERY [2334955]": "",
  "JAI MEWAR JUICE SEC 6": "",
  "JAY BHERAV DERY-Sect-11": "",
  "JMB DAIRY (SAVINA)": "",
  "KAMAKSHI STORE TITARDI": "",
  "KRISHNA DAIRY SEC 3": "",
  "KRISHNA DUDH DAIRY 14": "",
  "MAHAVEER KIRANA STOREA": "",
  "MANOJ KIRANA SEC 14": "",
  "MAYANK TRADERS SEC-4": "",
  "Mahalaxmi Misthan Bhandar(Sec.5)": "",
  "NEW BHERUNATH DUTH DAIRY": "",
  "OM KIRANA SEC 14": "",
  "PATEL DUDH DAIRY & KIRANA (EKLINGPURA)": "",
  "RAJLAXMI BAKERY(SEC.14)": "",
  "RAMA MEDICAL STORESEC-14": "",
  "SAI BAKERS SEC 5": "",
  "SALES RETURN - GST [SRGST-12]": "",
  "SK PROVISION STORE SEC 11": "",
  "VARSHA RESTAURANT(Titardi)": ""
}